Workbook

Sheet Inicio
A1: ETL + EDA — Tienda
A2: ETL (Extracción, Transformación y Carga) y EDA (Análisis Exploratorio de Datos), tomando como estructura guía el archivo EDA mercado.
A4: Mapa del libro
A5: Datos_Ventas | B5: Datos originales de ventas de la tienda.
A6: Datos_Inventario | B6: Datos originales de inventario.
A7: Datos_Compras | B7: Datos originales de compras.
A8: ETL_Ventas | B8: Limpieza, estandarización y métricas de ventas.
A9: ETL_Inventario | B9: Inventario transformado y stock restante.
A10: ETL_Compras | B10: Compras transformadas y total de gasto.
A11: Univariado | B11: Estadísticas descriptivas y distribución de ventas.
A12: Bivariado | B12: Ventas por producto, rentabilidad y relación cantidad-ingreso.
A13: Correlacion | B13: Correlación entre cantidad vendida y precio total.
A14: Conclusiones | B14: Hallazgos principales del análisis.
A17: Criterio de limpieza
A18: • | B18: Se estandarizaron nombres de productos: 'galletas red' → 'galleta red velvet chocolate' y 'galleta chocolate' → 'galletas chocolate'.
A19: • | B19: Se conservaron los datos de compras por separado porque corresponden a productos diferentes a los del inventario.
A20: • | B20: Las métricas de EDA se calculan sobre las ventas registradas; no se imputan ventas inexistentes.

Sheet Datos_Ventas
A1: Datos originales — Ventas
A2: id venta | B2: Producto | C2: Cantidad | D2: Costo U | E2: Costo Total | F2: Precio U | G2: Precio total | H2: Ganancia
A3: 1 | B3: tiramisu | C3: 2 | D3: 4 | E3: 8 | F3: 8 | G3: 16 | H3: 8
A4: 2 | B4: galleta red | C4: 1 | D4: 1 | E4: 2 | F4: 2 | G4: 4 | H4: 2
A5: 3 | B5: galleta chocolate | C5: 2 | D5: 1.5 | E5: 3 | F5: 2.5 | G5: 5 | H5: 2
A6: 4 | B6: galleta red | C6: 2 | D6: 2 | E6: 4 | F6: 4 | G6: 8 | H6: 4
A7: 5 | B7: galletas chocolate | C7: 2 | D7: 1.5 | E7: 3 | F7: 2.5 | G7: 5 | H7: 2

Sheet Datos_Inventario
A1: Datos originales — Inventario
A2: Producto | B2: inventario | C2: costo | D2: venta | E2: Inventario nuevo
A3: galletas chocolate | B3: 7 | C3: 1.5 | D3: 3 | E3: 5
A4: galletas mms chocolate | B4: 7 | C4: 2 | D4: 4
A5: galleta red velvet chocolate | B5: 7 | C5: 2 | D5: 4 | E5: 6
A6: cinamonroll | B6: 2 | C6: 4 | D6: 8
A7: tiramisu | B7: 2 | C7: 4 | D7: 8 | E7: 0
A8: cheese cake arandanos | B8: 2 | C8: 4 | D8: 8
A9: cheese cake cereza | B9: 2 | C9: 4 | D9: 8
A12: Presupuesto inicial | B12: 50
A13: Total Ventas | B13: 38
A14: Total Compras | B14: 35.5
A15: Balance | B15: =B12+B13-B14 -> 52.5

Sheet Datos_Compras
A1: Datos originales — Compras
A2: Compra | B2: Producto | C2: Cantidad | D2: Precio U | E2: Precio
A3: 1 | B3: Maquillaje | C3: 1 | D3: 10 | E3: 10
A4: 2 | B4: Uva | C4: 1 | D4: 10 | E4: 10
A5: 3 | B5: gloss | C5: 1 | D5: 6 | E5: 6
A6: 4 | B6: lapiz ojos | C6: 1 | D6: 5.5 | E6: 5.5
A7: 5 | B7: limas | C7: 2 | D7: 2 | E7: 4

Sheet ETL_Ventas
A1: ETL — Ventas
A3: id_venta | B3: producto_original | C3: producto_estandar | D3: cantidad | E3: costo_unitario | F3: costo_total | G3: precio_unitario | H3: precio_total | I3: ganancia | J3: margen_% | K3: validacion
A4: 1 | B4: tiramisu | C4: tiramisu | D4: 2 | E4: 4 | F4: 8 | G4: 8 | H4: 16 | I4: 8 | J4: =IF(H4=0,0,I4/H4) -> 0.5 | K4: =IF(AND(D4>0,F4=D4*E4,H4=D4*G4),"OK","REVISAR") -> OK
A5: 2 | B5: galleta red | C5: galleta red velvet chocolate | D5: 1 | E5: 1 | F5: 2 | G5: 2 | H5: 4 | I5: 2 | J5: =IF(H5=0,0,I5/H5) -> 0.5 | K5: =IF(AND(D5>0,F5=D5*E5,H5=D5*G5),"OK","REVISAR") -> REVISAR
A6: 3 | B6: galleta chocolate | C6: galletas chocolate | D6: 2 | E6: 1.5 | F6: 3 | G6: 2.5 | H6: 5 | I6: 2 | J6: =IF(H6=0,0,I6/H6) -> 0.4 | K6: =IF(AND(D6>0,F6=D6*E6,H6=D6*G6),"OK","REVISAR") -> OK
A7: 4 | B7: galleta red | C7: galleta red velvet chocolate | D7: 2 | E7: 2 | F7: 4 | G7: 4 | H7: 8 | I7: 4 | J7: =IF(H7=0,0,I7/H7) -> 0.5 | K7: =IF(AND(D7>0,F7=D7*E7,H7=D7*G7),"OK","REVISAR") -> OK
A8: 5 | B8: galletas chocolate | C8: galletas chocolate | D8: 2 | E8: 1.5 | F8: 3 | G8: 2.5 | H8: 5 | I8: 2 | J8: =IF(H8=0,0,I8/H8) -> 0.4 | K8: =IF(AND(D8>0,F8=D8*E8,H8=D8*G8),"OK","REVISAR") -> OK
A9: TOTAL | D9: =SUM(D4:D8) -> 9 | F9: =SUM(F4:F8) -> 20 | H9: =SUM(H4:H8) -> 38 | I9: =SUM(I4:I8) -> 18

Sheet ETL_Inventario
A1: ETL — Inventario
A3: producto | B3: stock_inicial | C3: costo_unitario | D3: precio_venta | E3: cantidad_vendida | F3: stock_final | G3: valor_stock_final | H3: estado
A4: galletas chocolate | B4: 7 | C4: 1.5 | D4: 3 | E4: 4 | F4: =B4-E4 -> 3 | G4: =F4*C4 -> 4.5 | H4: =IF(F4<0,"Stock negativo",IF(F4=0,"Agotado","Disponible")) -> Disponible
A5: galletas mms chocolate | B5: 7 | C5: 2 | D5: 4 | E5: 0 | F5: =B5-E5 -> 7 | G5: =F5*C5 -> 14 | H5: =IF(F5<0,"Stock negativo",IF(F5=0,"Agotado","Disponible")) -> Disponible
A6: galleta red velvet chocolate | B6: 7 | C6: 2 | D6: 4 | E6: 3 | F6: =B6-E6 -> 4 | G6: =F6*C6 -> 8 | H6: =IF(F6<0,"Stock negativo",IF(F6=0,"Agotado","Disponible")) -> Disponible
A7: cinamonroll | B7: 2 | C7: 4 | D7: 8 | E7: 0 | F7: =B7-E7 -> 2 | G7: =F7*C7 -> 8 | H7: =IF(F7<0,"Stock negativo",IF(F7=0,"Agotado","Disponible")) -> Disponible
A8: tiramisu | B8: 2 | C8: 4 | D8: 8 | E8: 2 | F8: =B8-E8 -> 0 | G8: =F8*C8 -> 0 | H8: =IF(F8<0,"Stock negativo",IF(F8=0,"Agotado","Disponible")) -> Agotado
A9: cheese cake arandanos | B9: 2 | C9: 4 | D9: 8 | E9: 0 | F9: =B9-E9 -> 2 | G9: =F9*C9 -> 8 | H9: =IF(F9<0,"Stock negativo",IF(F9=0,"Agotado","Disponible")) -> Disponible
A10: cheese cake cereza | B10: 2 | C10: 4 | D10: 8 | E10: 0 | F10: =B10-E10 -> 2 | G10: =F10*C10 -> 8 | H10: =IF(F10<0,"Stock negativo",IF(F10=0,"Agotado","Disponible")) -> Disponible

Sheet ETL_Compras
A1: ETL — Compras
A3: id_compra | B3: producto | C3: cantidad | D3: precio_unitario | E3: precio_total | F3: categoria_producto | G3: validacion
A4: 1 | B4: Maquillaje | C4: 1 | D4: 10 | E4: 10 | F4: Producto externo | G4: =IF(E4=C4*D4,"OK","REVISAR") -> OK
A5: 2 | B5: Uva | C5: 1 | D5: 10 | E5: 10 | F5: Producto externo | G5: =IF(E5=C5*D5,"OK","REVISAR") -> OK
A6: 3 | B6: gloss | C6: 1 | D6: 6 | E6: 6 | F6: Producto externo | G6: =IF(E6=C6*D6,"OK","REVISAR") -> OK
A7: 4 | B7: lapiz ojos | C7: 1 | D7: 5.5 | E7: 5.5 | F7: Producto externo | G7: =IF(E7=C7*D7,"OK","REVISAR") -> OK
A8: 5 | B8: limas | C8: 2 | D8: 2 | E8: 4 | F8: Producto externo | G8: =IF(E8=C8*D8,"OK","REVISAR") -> OK
A9: TOTAL | E9: =SUM(E4:E8) -> 35.5

Sheet Univariado
A1: EDA — Univariado
A3: Estadísticas de precio total por venta
A4: Conteo | B4: =COUNT(ETL_Ventas!$H$4:$H$8) -> 5
A5: Promedio | B5: =AVERAGE(ETL_Ventas!$H$4:$H$8) -> 7.6
A6: Mínimo | B6: =MIN(ETL_Ventas!$H$4:$H$8) -> 4
A7: Máximo | B7: =MAX(ETL_Ventas!$H$4:$H$8) -> 16
A8: Desviación estándar | B8: =_xlfn.STDEV.S(ETL_Ventas!$H$4:$H$8) -> 4.929503
A9: Q1 | B9: =_xlfn.QUARTILE.INC(ETL_Ventas!$H$4:$H$8,1) -> 5
A10: Mediana | B10: =MEDIAN(ETL_Ventas!$H$4:$H$8) -> 5
A11: Q3 | B11: =_xlfn.QUARTILE.INC(ETL_Ventas!$H$4:$H$8,3) -> 8
A12: RIC | B12: =B11-B9 -> 3
A13: Límite inferior outlier | B13: =B9-1.5*B12 -> 0.5
A14: Límite superior outlier | B14: =B11+1.5*B12 -> 12.5
A17: Resumen por producto
A18: Producto | B18: Cantidad vendida | C18: Ingreso total | D18: Ganancia total
A19: tiramisu | B19: =SUMIF(ETL_Ventas!$C$4:$C$8,A19,ETL_Ventas!$D$4:$D$8) -> 2 | C19: =SUMIF(ETL_Ventas!$C$4:$C$8,A19,ETL_Ventas!$H$4:$H$8) -> 16 | D19: =SUMIF(ETL_Ventas!$C$4:$C$8,A19,ETL_Ventas!$I$4:$I$8) -> 8
A20: galleta red velvet chocolate | B20: =SUMIF(ETL_Ventas!$C$4:$C$8,A20,ETL_Ventas!$D$4:$D$8) -> 3 | C20: =SUMIF(ETL_Ventas!$C$4:$C$8,A20,ETL_Ventas!$H$4:$H$8) -> 12 | D20: =SUMIF(ETL_Ventas!$C$4:$C$8,A20,ETL_Ventas!$I$4:$I$8) -> 6
A21: galletas chocolate | B21: =SUMIF(ETL_Ventas!$C$4:$C$8,A21,ETL_Ventas!$D$4:$D$8) -> 4 | C21: =SUMIF(ETL_Ventas!$C$4:$C$8,A21,ETL_Ventas!$H$4:$H$8) -> 10 | D21: =SUMIF(ETL_Ventas!$C$4:$C$8,A21,ETL_Ventas!$I$4:$I$8) -> 4

Sheet Bivariado
A1: EDA — Bivariado
A3: Ingreso y rentabilidad por producto
A4: Producto | B4: Cantidad | C4: Ingreso total | D4: Ganancia total | E4: Margen %
A5: tiramisu | B5: =SUMIF(ETL_Ventas!$C$4:$C$8,A5,ETL_Ventas!$D$4:$D$8) -> 2 | C5: =SUMIF(ETL_Ventas!$C$4:$C$8,A5,ETL_Ventas!$H$4:$H$8) -> 16 | D5: =SUMIF(ETL_Ventas!$C$4:$C$8,A5,ETL_Ventas!$I$4:$I$8) -> 8 | E5: =IF(C5=0,0,D5/C5) -> 0.5
A6: galleta red velvet chocolate | B6: =SUMIF(ETL_Ventas!$C$4:$C$8,A6,ETL_Ventas!$D$4:$D$8) -> 3 | C6: =SUMIF(ETL_Ventas!$C$4:$C$8,A6,ETL_Ventas!$H$4:$H$8) -> 12 | D6: =SUMIF(ETL_Ventas!$C$4:$C$8,A6,ETL_Ventas!$I$4:$I$8) -> 6 | E6: =IF(C6=0,0,D6/C6) -> 0.5
A7: galletas chocolate | B7: =SUMIF(ETL_Ventas!$C$4:$C$8,A7,ETL_Ventas!$D$4:$D$8) -> 4 | C7: =SUMIF(ETL_Ventas!$C$4:$C$8,A7,ETL_Ventas!$H$4:$H$8) -> 10 | D7: =SUMIF(ETL_Ventas!$C$4:$C$8,A7,ETL_Ventas!$I$4:$I$8) -> 4 | E7: =IF(C7=0,0,D7/C7) -> 0.4
A10: Relación cantidad vs ingreso
A11: La gráfica muestra si vender más unidades tiende a aumentar el ingreso de una transacción.
A14: Indicador de rentabilidad
A15: Margen global | B15: =SUM(ETL_Ventas!I4:I8)/SUM(ETL_Ventas!H4:H8) -> 0.47368421
A16: Ingreso total | B16: =SUM(ETL_Ventas!H4:H8) -> 38
A17: Ganancia total | B17: =SUM(ETL_Ventas!I4:I8) -> 18
A18: Gasto total compras | B18: =SUM(ETL_Compras!E4:E8) -> 35.5

Sheet Correlacion
A1: EDA — Correlación
A3: Correlación entre cantidad vendida y precio total
A4: Coeficiente de correlación | B4: =CORREL(ETL_Ventas!$D$4:$D$8,ETL_Ventas!$H$4:$H$8) -> 0.40824829
A5: Interpretación | B5: =IF(ABS(B4)>=0.7,"Correlación fuerte",IF(ABS(B4)>=0.3,"Correlación moderada","Correlación débil"))&IF(B4>=0," positiva."," negativa.") -> Correlación moderada positiva.
A7: Nota | B7: La correlación describe asociación, no demuestra causalidad.

Sheet Conclusiones
A1: Conclusiones
A2: Hallazgos obtenidos a partir de las hojas Univariado, Bivariado y Correlacion.
A4: Hallazgo 1 | B4: El producto con mayor cantidad vendida es galletas chocolate, con 4 unidades.
A5: Hallazgo 2 | B5: Tiramisú genera el mayor ingreso por producto y también la mayor ganancia total.
A6: Hallazgo 3 | B6: Las ventas registran $38,00 de ingreso total y $18,00 de ganancia, equivalente a un margen global cercano al 47,4%.
A7: Hallazgo 4 | B7: El inventario transformado permite identificar el stock restante después de descontar las unidades vendidas.
A8: Hallazgo 5 | B8: La relación entre cantidad y precio total es positiva y moderada; vender más unidades tiende a asociarse con mayores ingresos, aunque no de forma perfecta.
A9: Hipótesis a validar | B9: Si la tienda aumenta la cantidad de unidades vendidas por transacción, podría aumentar el ingreso total, manteniendo precios y costos controlados.
